textcl/__init__.py
textcl/outliers_detection.py
textcl/preprocessing.py
textcl-1.0.1.dist-info/LICENSE
textcl-1.0.1.dist-info/METADATA
textcl-1.0.1.dist-info/WHEEL
textcl-1.0.1.dist-info/top_level.txt
textcl-1.0.1.dist-info/RECORD
