Metadata-Version: 2.1
Name: textcl
Version: 1.0.1
Summary: Text preprocessing package for use in NLP tasks
Home-page: https://github.com/alinapetukhova/textcl
Download-URL: https://github.com/alinapetukhova/textcl/archive/refs/tags/v.1.0.1.tar.gz
Author: Alina Petukhova
Author-email: petukhova.alina@gmail.com
License: MIT
Keywords: NLP,Text preprocessing,Outlier detection
Classifier: Development Status :: 4 - Beta
Classifier: Intended Audience :: Developers
Classifier: Topic :: Scientific/Engineering :: Artificial Intelligence
Classifier: License :: OSI Approved :: MIT License
Classifier: Programming Language :: Python :: 3.8
Classifier: Programming Language :: Python :: 3.9
Classifier: Programming Language :: Python :: 3.10
Classifier: Programming Language :: Python :: 3.11
Classifier: Programming Language :: Python :: 3.12
Requires-Python: >=3.8
License-File: LICENSE
Requires-Dist: numpy>=1.21.3
Requires-Dist: pandas>=1.4.3
Requires-Dist: torch>=1.5.0
Requires-Dist: pytorch-pretrained-bert>=0.6.2
Requires-Dist: langdetect>=1.0.8
Requires-Dist: lxml>=4.6.2
Requires-Dist: protobuf>=3.14.0
Requires-Dist: nltk>=3.4.5
Requires-Dist: scikit-learn>=0.24.1
Requires-Dist: testresources>=2.0.1
